simopt/GUI.py
simopt/__init__.py
simopt/__main__.py
simopt/base.py
simopt/bootstrap.py
simopt/curve.py
simopt/curve_utils.py
simopt/data_farming_base.py
simopt/directory.py
simopt/experiment_base.py
simopt/experimental.py
simopt/feasibility.py
simopt/input_models.py
simopt/model.py
simopt/plot_type.py
simopt/problem.py
simopt/problem_types.py
simopt/solver.py
simopt/utils.py
simopt/utils.pyi
simopt/data_farming/data_farming_core.py
simopt/data_farming/nolhs.py
simopt/data_farming/nolhs_design_table.npz
simopt/experiment/__init__.py
simopt/experiment/multiple.py
simopt/experiment/post_normalize.py
simopt/experiment/single.py
simopt/gui/data_farming_window.py
simopt/gui/df_object.py
simopt/gui/main_menu.py
simopt/gui/new_experiment_window.py
simopt/gui/plot_window.py
simopt/gui/toplevel_custom.py
simopt/models/__init__.py
simopt/models/_ext.py
simopt/models/amusementpark.py
simopt/models/chessmm.py
simopt/models/cntnv.py
simopt/models/contam.py
simopt/models/dualsourcing.py
simopt/models/dynamnews.py
simopt/models/ermexample.py
simopt/models/example.py
simopt/models/facilitysizing.py
simopt/models/fixedsan.py
simopt/models/hotel.py
simopt/models/ironore.py
simopt/models/mm1queue.py
simopt/models/network.py
simopt/models/paramesti.py
simopt/models/rmitd.py
simopt/models/san.py
simopt/models/sscont.py
simopt/models/tableallocation.py
simopt/plots/__init__.py
simopt/plots/area_scatterplot.py
simopt/plots/feasibility_progress.py
simopt/plots/progress_curve.py
simopt/plots/solvability_cdf.py
simopt/plots/solvability_profile.py
simopt/plots/terminal_feasibility.py
simopt/plots/terminal_progress.py
simopt/plots/terminal_scatterplot.py
simopt/plots/utils.py
simopt/solvers/__init__.py
simopt/solvers/adam.py
simopt/solvers/aloe.py
simopt/solvers/astrodf.py
simopt/solvers/fcsa.py
simopt/solvers/neldmd.py
simopt/solvers/randomsearch.py
simopt/solvers/spsa.py
simopt/solvers/strong.py
simopt/solvers/utils.py
simoptlib-1.2.2.post0.dist-info/licenses/LICENSE
simoptlib-1.2.2.post0.dist-info/METADATA
simoptlib-1.2.2.post0.dist-info/WHEEL
simoptlib-1.2.2.post0.dist-info/top_level.txt
simoptlib-1.2.2.post0.dist-info/RECORD
