Metadata-Version: 2.4
Name: simoptlib
Version: 1.2.2.post0
Summary: A testbed for simulation-optimization experiments.
Author-email: David Eckman <eckman@tamu.edu>, Shane Henderson <sgh9@cornell.edu>, Sara Shashaani <sshasha2@ncsu.edu>, William Grochocinski <williamgrochocinski@gmail.com>
License: MIT License
Project-URL: Homepage, https://github.com/simopt-admin/simopt
Project-URL: Documentation, https://simopt.readthedocs.io/en/latest/
Classifier: Programming Language :: Python :: 3
Classifier: License :: OSI Approved :: MIT License
Classifier: Operating System :: OS Independent
Requires-Python: <3.14,>=3.11
License-File: LICENSE
Requires-Dist: boltons>=25.0.0
Requires-Dist: cvxpy>=1.7.3
Requires-Dist: joblib>=1.5.2
Requires-Dist: matplotlib>=3.10.7
Requires-Dist: mrg32k3a[rust]>=2.0.0
Requires-Dist: numpy>=2.3.4
Requires-Dist: pandas>=2.3.3
Requires-Dist: pillow>=12.0.0
Requires-Dist: pydantic>=2.12.3
Requires-Dist: scipy>=1.16.3
Requires-Dist: seaborn>=0.13.2
Provides-Extra: dev
Requires-Dist: jupytext>=1.18.1; extra == "dev"
Requires-Dist: pytest-xdist>=3.8.0; extra == "dev"
Requires-Dist: pytest>=9.0.1; extra == "dev"
Requires-Dist: ruff>=0.14.2; extra == "dev"
Requires-Dist: ty>=0.0.1a26; extra == "dev"
Provides-Extra: docs
Requires-Dist: sphinx>=8.2.3; extra == "docs"
Requires-Dist: sphinx-autoapi>=3.6.1; extra == "docs"
Requires-Dist: sphinx-rtd-theme>=3.0.2; extra == "docs"
Provides-Extra: notebooks
Requires-Dist: ipykernel>=7.1.0; extra == "notebooks"
Provides-Extra: ext
Requires-Dist: simopt-extensions; extra == "ext"
Dynamic: license-file
